MANIFEST.in
README.md
README.rst
requirements.txt
setup.py
caesar/__init__.py
caesar/connection.py
caesar/logger.py
caesar/mail.py
caesar/main.py
caesar/save_credential.py
caesar/utils.py
caesar.egg-info/PKG-INFO
caesar.egg-info/SOURCES.txt
caesar.egg-info/dependency_links.txt
caesar.egg-info/entry_points.txt
caesar.egg-info/requires.txt
caesar.egg-info/top_level.txt