Metadata-Version: 1.0
Name: caesar
Version: 0.1.2
Summary: A command line e-mail helper
Home-page: https://github.com/tanjot/caesar
Author: Tanjot Kaur
Author-email: tanjot28@gmail.com
License: GPLv3
Platform: UNKNOWN
